lark_logging/__init__.py
lark_logging/handler.py
lark_logging/models.py
lark_logging/utils.py
lark_logging_handler-0.1.0.dist-info/METADATA
lark_logging_handler-0.1.0.dist-info/WHEEL
lark_logging_handler-0.1.0.dist-info/licenses/LICENSE
lark_logging_handler-0.1.0.dist-info/RECORD
