Metadata-Version: 2.4
Name: lark-logging-handler
Version: 0.1.0
Summary: A Python logging handler that sends log messages to Lark (Feishu) as beautiful interactive cards.
Author-email: Gtio <gtoxlili@outlook.com>
License-Expression: GPL-3.0-or-later
License-File: LICENSE
Requires-Python: >=3.13
Requires-Dist: lark-oapi>=1.4.14
Requires-Dist: python-logstash>=0.4.8
